ilastik/napari/__init__.py
ilastik/napari/classifier.py
ilastik/napari/filters.py
ilastik/napari/gui.py
ilastik/napari/plugin.py
ilastik/napari/plugin.toml
ilastik_napari-0.3.1.dist-info/licenses/LICENSE
ilastik_napari-0.3.1.dist-info/METADATA
ilastik_napari-0.3.1.dist-info/WHEEL
ilastik_napari-0.3.1.dist-info/entry_points.txt
ilastik_napari-0.3.1.dist-info/top_level.txt
ilastik_napari-0.3.1.dist-info/RECORD
