Metadata-Version: 2.4
Name: ilastik-napari
Version: 0.3.1
Summary: ilastik plugin for napari
Author-email: Emil Melnikov <emilmelnikov@gmail.com>
License: MIT
Project-URL: homepage, https://github.com/ilastik/ilastik-napari
Classifier: Development Status :: 2 - Pre-Alpha
Classifier: Environment :: Plugins
Classifier: Intended Audience :: End Users/Desktop
Classifier: Intended Audience :: Science/Research
Classifier: License :: OSI Approved :: MIT License
Classifier: Framework :: napari
Classifier: Operating System :: MacOS
Classifier: Operating System :: MacOS :: MacOS X
Classifier: Operating System :: Microsoft :: Windows
Classifier: Operating System :: POSIX
Classifier: Operating System :: POSIX :: Linux
Classifier: Programming Language :: Python :: 3
Classifier: Programming Language :: Python :: 3 :: Only
Classifier: Programming Language :: Python :: Implementation :: CPython
Classifier: Topic :: Scientific/Engineering
Classifier: Topic :: Scientific/Engineering :: Image Processing
Requires-Python: >=3.8
License-File: LICENSE
Requires-Dist: napari>=0.4.13
Requires-Dist: numpy>=1.20
Requires-Dist: qtpy
Requires-Dist: scikit-learn
Requires-Dist: sparse
Dynamic: license-file
